diff_checkpoint/__init__.py
diff_checkpoint/diff_checkpoint.py
diff_checkpoint/first_element.py
pytorch_diff_checkpoint-1.2.0.dist-info/METADATA
pytorch_diff_checkpoint-1.2.0.dist-info/WHEEL
pytorch_diff_checkpoint-1.2.0.dist-info/RECORD
