Metadata-Version: 2.1
Name: pytorch-diff-checkpoint
Version: 1.2.0
Summary: A PyTorch helper library designed to save only the changes in a fine-tuned base model.
Author: Richard Löwenström
Author-email: samedii@gmail.com
Requires-Python: >=3.9,<4.0
Classifier: Programming Language :: Python :: 3
Classifier: Programming Language :: Python :: 3.9
Classifier: Programming Language :: Python :: 3.10
Classifier: Programming Language :: Python :: 3.11
Classifier: Programming Language :: Python :: 3.12
Classifier: Programming Language :: Python :: 3.13
Requires-Dist: torch (>=2.0.0,<3.0.0)
